microdaq/__init__.py
microdaq/cli.py
microdaq/ctypes_mlink.py
microdaq/device.py
microdaq/armel/libmlink.so
microdaq/x64/MLink64.dll
microdaq/x64/libmlink.dylib
microdaq/x64/libmlink.so
microdaq/x86/MLink32.dll
microdaq/x86/libmlink.so
microdaq-1.4.0.dist-info/LICENSE.md
microdaq-1.4.0.dist-info/METADATA
microdaq-1.4.0.dist-info/WHEEL
microdaq-1.4.0.dist-info/top_level.txt
microdaq-1.4.0.dist-info/RECORD
