Metadata-Version: 2.1
Name: microdaq
Version: 1.4.0
Summary: A Python programming interface for MicroDAQ DAQ devices.
Home-page: http://www.microdaq.org/software/python/using-microdaq-with-python.html
Author: Witczeko
Author-email: witczenko@gmail.com
Maintainer: Witczeko
Maintainer-email: witczenko@gmail.com
License: BSD-3-Clause
Project-URL: Code, https://github.com/microdaq/PyMLink
Project-URL: Issue tracker, https://github.com/microdaq/PyMLink/issues
Platform: UNKNOWN
Classifier: Development Status :: 4 - Beta
Classifier: Operating System :: OS Independent
Classifier: Topic :: System :: Hardware :: Hardware Drivers
Classifier: Programming Language :: Python :: 2.7
Classifier: Programming Language :: Python :: 3
Requires-Python: >=2.7
